taskiq_pg/__init__.py
taskiq_pg/broker.py
taskiq_pg/broker_queries.py
taskiq_pg/exceptions.py
taskiq_pg/py.typed
taskiq_pg/queries.py
taskiq_pg/result_backend.py
taskiq_pg-0.2.0.dist-info/METADATA
taskiq_pg-0.2.0.dist-info/WHEEL
taskiq_pg-0.2.0.dist-info/licenses/LICENSE
taskiq_pg-0.2.0.dist-info/RECORD
