Metadata-Version: 2.4
Name: taskiq-pg
Version: 0.2.0
Summary: AsyncPG and PostgreSQL integration for taskiq
Project-URL: Repository, https://github.com/karoo-ca/taskiq-pg
Author-email: Oliver Lambson <ollie@karoo.ca>
License-File: LICENSE
Keywords: async,asyncpg,distributed,postgresql,result_backend,taskiq,tasks
Classifier: Programming Language :: Python
Classifier: Programming Language :: Python :: 3
Classifier: Programming Language :: Python :: 3 :: Only
Classifier: Programming Language :: Python :: 3.9
Classifier: Programming Language :: Python :: 3.10
Classifier: Programming Language :: Python :: 3.11
Classifier: Programming Language :: Python :: 3.12
Classifier: Programming Language :: Python :: 3.13
Requires-Python: >=3.9
Requires-Dist: asyncpg>=0.30.0
Requires-Dist: taskiq>=0.11.10
